<?xml version="1.0" encoding="UTF-8"?>
<tv generator-info-name="WebGrab+Plus/w MDB &amp; REX Postprocess -- version  V5.6.0.0 -- Jan van Straaten" generator-info-url="http://www.webgrabplus.com">
  <channel id="Anime_Visión">
    <display-name lang="es">Anime Visión</display-name>
    <url>http://www.tivify.tv</url>
  </channel>
  <channel id="Anime_Visión_Classics">
    <display-name lang="es">Anime Visión Classics</display-name>
    <url>http://www.tivify.tv</url>
  </channel>
  <channel id="Yu-Gi-Oh!">
    <display-name lang="es">Yu-Gi-Oh!</display-name>
    <url>http://www.tivify.tv</url>
  </channel>
  <channel id="Beyblade_FAST">
    <display-name lang="es">Beyblade</display-name>
    <url>http://www.tivify.tv</url>
  </channel>
  <channel id="Pocoyó_y_Más">
    <display-name lang="es">Pocoyó y Más</display-name>
    <url>http://www.tivify.tv</url>
  </channel>
  <channel id="Águila_Roja_FAST">
    <display-name lang="es">Águila Roja</display-name>
    <url>http://www.tivify.tv</url>
  </channel>
  <channel id="Curro_Jiménez_FAST">
    <display-name lang="es">Curro Jiménez</display-name>
    <url>http://www.tivify.tv</url>
  </channel>
  <channel id="Ana_y_los_7_FAST">
    <display-name lang="es">Ana y los 7</display-name>
    <url>http://www.tivify.tv</url>
  </channel>
  <channel id="Cines_Verdi_TV">
    <display-name lang="es">Cines Verdi TV</display-name>
    <url>http://www.tivify.tv</url>
  </channel>
  <channel id="Cine_Feel_Good_Verdi_TV">
    <display-name lang="es">Cine Feel Good Verdi TV</display-name>
    <url>http://www.tivify.tv</url>
  </channel>
</tv>